osvm/Test.py
osvm/osvm.py
osvm/tdsvm.py
osvm-1.3.0.dist-info/DESCRIPTION.rst
osvm-1.3.0.dist-info/METADATA
osvm-1.3.0.dist-info/RECORD
osvm-1.3.0.dist-info/WHEEL
osvm-1.3.0.dist-info/metadata.json
osvm-1.3.0.dist-info/top_level.txt
